KrxDataReader/__init__.py
KrxDataReader/fetcher.py
KrxDataReader/reader.py
KrxDataReader/data_reader/__init__.py
KrxDataReader/data_reader/base.py
KrxDataReader/data_reader/etc.py
KrxDataReader/data_reader/foreign.py
KrxDataReader/data_reader/sector.py
KrxDataReader/data_reader/trader.py
KrxDataReader-1.0.0.dist-info/METADATA
KrxDataReader-1.0.0.dist-info/WHEEL
KrxDataReader-1.0.0.dist-info/top_level.txt
KrxDataReader-1.0.0.dist-info/RECORD
